LICENSE
README.md
setup.py
star_resty/__init__.py
star_resty/exceptions.py
star_resty/inject.py
star_resty.egg-info/PKG-INFO
star_resty.egg-info/SOURCES.txt
star_resty.egg-info/dependency_links.txt
star_resty.egg-info/not-zip-safe
star_resty.egg-info/requires.txt
star_resty.egg-info/top_level.txt
star_resty/apidocs/__init__.py
star_resty/apidocs/operation.py
star_resty/apidocs/request.py
star_resty/apidocs/response.py
star_resty/apidocs/route.py
star_resty/apidocs/setup.py
star_resty/apidocs/template.html
star_resty/apidocs/utils.py
star_resty/method/__init__.py
star_resty/method/meta.py
star_resty/method/method.py
star_resty/method/parser.py
star_resty/method/render.py
star_resty/operation/__init__.py
star_resty/operation/schema.py
star_resty/payload/__init__.py
star_resty/payload/base.py
star_resty/payload/form.py
star_resty/payload/header.py
star_resty/payload/json.py
star_resty/payload/path.py
star_resty/payload/query.py
star_resty/payload/upload.py
star_resty/serializers/__init__.py
star_resty/serializers/json.py
star_resty/serializers/serializer.py