Metadata-Version: 2.1
Name: star-resty
Version: 0.0.20
Summary: The web framework
Home-page: https://github.com/slv0/start_resty
Author: Slava Cheremushkin
Author-email: slv0.chr@gmail.com
License: BSD
Platform: UNKNOWN
Classifier: Development Status :: 3 - Alpha
Classifier: Environment :: Web Environment
Classifier: Intended Audience :: Developers
Classifier: License :: OSI Approved :: BSD License
Classifier: Operating System :: OS Independent
Classifier: Topic :: Internet :: WWW/HTTP
Classifier: Programming Language :: Python :: 3.7
Requires-Python: >=3.7
